skore_hub_project/__init__.py
skore_hub_project/protocol.py
skore_hub_project/artifact/__init__.py
skore_hub_project/artifact/artifact.py
skore_hub_project/artifact/serializer.py
skore_hub_project/artifact/upload.py
skore_hub_project/artifact/media/__init__.py
skore_hub_project/artifact/media/data.py
skore_hub_project/artifact/media/feature_importance.py
skore_hub_project/artifact/media/media.py
skore_hub_project/artifact/media/model.py
skore_hub_project/artifact/media/performance.py
skore_hub_project/artifact/pickle/__init__.py
skore_hub_project/artifact/pickle/pickle.py
skore_hub_project/authentication/__init__.py
skore_hub_project/authentication/login.py
skore_hub_project/authentication/logout.py
skore_hub_project/authentication/token.py
skore_hub_project/authentication/uri.py
skore_hub_project/client/__init__.py
skore_hub_project/client/client.py
skore_hub_project/metric/__init__.py
skore_hub_project/metric/accuracy.py
skore_hub_project/metric/brier_score.py
skore_hub_project/metric/log_loss.py
skore_hub_project/metric/metric.py
skore_hub_project/metric/precision.py
skore_hub_project/metric/r2.py
skore_hub_project/metric/recall.py
skore_hub_project/metric/rmse.py
skore_hub_project/metric/roc_auc.py
skore_hub_project/metric/timing.py
skore_hub_project/project/__init__.py
skore_hub_project/project/project.py
skore_hub_project/report/__init__.py
skore_hub_project/report/cross_validation_report.py
skore_hub_project/report/estimator_report.py
skore_hub_project/report/report.py
skore_hub_project-0.0.14.dist-info/METADATA
skore_hub_project-0.0.14.dist-info/WHEEL
skore_hub_project-0.0.14.dist-info/entry_points.txt
skore_hub_project-0.0.14.dist-info/licenses/LICENSE
skore_hub_project-0.0.14.dist-info/RECORD
