Metadata-Version: 2.4
Name: skore-hub-project
Version: 0.0.14
Maintainer-email: skore developers <skore@signal.probabl.ai>
License-Expression: MIT
License-File: LICENSE
Requires-Python: >=3.10
Requires-Dist: blake3
Requires-Dist: httpx
Requires-Dist: joblib
Requires-Dist: matplotlib
Requires-Dist: numpy
Requires-Dist: orjson
Requires-Dist: pydantic
Requires-Dist: rich
Requires-Dist: scikit-learn
Provides-Extra: test
Requires-Dist: pandas-stubs; extra == 'test'
Requires-Dist: pre-commit; extra == 'test'
Requires-Dist: pytest; extra == 'test'
Requires-Dist: pytest-cov; extra == 'test'
Requires-Dist: pytest-order; extra == 'test'
Requires-Dist: pytest-randomly; extra == 'test'
Requires-Dist: pytest-xdist; extra == 'test'
Requires-Dist: respx; extra == 'test'
Requires-Dist: skore>=0.10.3; extra == 'test'
Requires-Dist: xdoctest; extra == 'test'
